test_nester_micah/__init__.py
test_nester_micah-1.3.0.dist-info/LICENSE
test_nester_micah-1.3.0.dist-info/METADATA
test_nester_micah-1.3.0.dist-info/WHEEL
test_nester_micah-1.3.0.dist-info/top_level.txt
test_nester_micah-1.3.0.dist-info/RECORD
