Metadata-Version: 2.1
Name: test-nester-micah
Version: 1.3.0
Summary: A simple but memorable package
Home-page: https://github.com/micang404/StudyHeadFirstPython
Author: Vincent
Author-email: micahkabala@outlook.com
License: UNKNOWN
Platform: UNKNOWN
Classifier: Programming Language :: Python :: 3
Classifier: License :: OSI Approved :: MIT License
Classifier: Operating System :: OS Independent
